docker_cron/__init__.py
docker_cron-0.4.1.dist-info/METADATA
docker_cron-0.4.1.dist-info/WHEEL
docker_cron-0.4.1.dist-info/entry_points.txt
docker_cron-0.4.1.dist-info/top_level.txt
docker_cron-0.4.1.dist-info/RECORD
